django_ctb/__init__.py
django_ctb/admin.py
django_ctb/apps.py
django_ctb/models.py
django_ctb/services.py
django_ctb/tasks.py
django_ctb/migrations/0001_initial.py
django_ctb/migrations/__init__.py
django_ctb/mouser/__init__.py
django_ctb/mouser/client.py
django_ctb/mouser/services.py
django_ctb/templates/admin/inventory/project_version_bom.html
django_ctb/templates/admin/inventory/projectversion/change_form.html
django_ctb-0.0.1.dist-info/LICENSE.txt
django_ctb-0.0.1.dist-info/METADATA
django_ctb-0.0.1.dist-info/WHEEL
django_ctb-0.0.1.dist-info/top_level.txt
django_ctb-0.0.1.dist-info/RECORD
